bd_vslot/__init__.py
bd_vslot/rail.py
bd_vslot/utils/__init__.py
bd_vslot/utils/array.py
bd_vslot-0.0.1.dist-info/LICENSE
bd_vslot-0.0.1.dist-info/METADATA
bd_vslot-0.0.1.dist-info/WHEEL
bd_vslot-0.0.1.dist-info/top_level.txt
bd_vslot-0.0.1.dist-info/RECORD
